LICENSE
MANIFEST.in
README.md
setup.cfg
setup.py
trex_model.egg-info/PKG-INFO
trex_model.egg-info/SOURCES.txt
trex_model.egg-info/dependency_links.txt
trex_model.egg-info/requires.txt
trex_model.egg-info/top_level.txt
trexmodel/__init__.py
trexmodel/conf.py
trexmodel/pos_conf.py
trexmodel/program_conf.py
trexmodel/models/__init__.py
trexmodel/models/merchant_helpers.py
trexmodel/models/model_decorator.py
trexmodel/models/prepaid_helpers.py
trexmodel/models/datastore/__init__.py
trexmodel/models/datastore/admin_models.py
trexmodel/models/datastore/analytic_models.py
trexmodel/models/datastore/app_models.py
trexmodel/models/datastore/coporate_models.py
trexmodel/models/datastore/customer_model_helpers.py
trexmodel/models/datastore/customer_models.py
trexmodel/models/datastore/fan_club_models.py
trexmodel/models/datastore/fb_subsriber_models.py
trexmodel/models/datastore/import_models.py
trexmodel/models/datastore/inventory_model.py
trexmodel/models/datastore/loyalty_models.py
trexmodel/models/datastore/lucky_draw_models.py
trexmodel/models/datastore/marketing_models.py
trexmodel/models/datastore/membership_models.py
trexmodel/models/datastore/merchant_models.py
trexmodel/models/datastore/merchant_promotion_models.py
trexmodel/models/datastore/message_model_helper.py
trexmodel/models/datastore/message_models.py
trexmodel/models/datastore/model_decorators.py
trexmodel/models/datastore/ndb_models.py
trexmodel/models/datastore/partnership_models.py
trexmodel/models/datastore/pos_models.py
trexmodel/models/datastore/prepaid_models.py
trexmodel/models/datastore/product_models.py
trexmodel/models/datastore/program_models.py
trexmodel/models/datastore/rating_models.py
trexmodel/models/datastore/recruit_models.py
trexmodel/models/datastore/redeem_models.py
trexmodel/models/datastore/redemption_catalogue_models.py
trexmodel/models/datastore/referral_program_model.py
trexmodel/models/datastore/reward_models.py
trexmodel/models/datastore/spending_base_program_model.py
trexmodel/models/datastore/support_models.py
trexmodel/models/datastore/system_models.py
trexmodel/models/datastore/task_models.py
trexmodel/models/datastore/test_models.py
