Metadata-Version: 2.4
Name: trex_model
Version: 1.7.3
Summary: TRex database module package
Home-page: https://bitbucket.org/lokjac/trex-model
Author: Jack Lok
Author-email: sglok77@gmail.com
Classifier: Programming Language :: Python :: 3
Classifier: License :: OSI Approved :: MIT License
Classifier: Operating System :: OS Independent
License-File: LICENSE
Requires-Dist: google-cloud-firestore
Requires-Dist: google_cloud_datastore
Requires-Dist: google-cloud-ndb
Requires-Dist: six
Requires-Dist: trex-lib
Requires-Dist: flask-login==0.6.2
Dynamic: author
Dynamic: author-email
Dynamic: classifier
Dynamic: description
Dynamic: description-content-type
Dynamic: home-page
Dynamic: license-file
Dynamic: requires-dist
Dynamic: summary
